mqss/__init__.py
mqss/qir_qiskit/__init__.py
mqss/qir_qiskit/elements.py
mqss/qir_qiskit/regex.py
mqss/qir_qiskit/translate.py
mqss/qir_qiskit/visitor.py
mqss_qir_qiskit-0.1.0.dist-info/METADATA
mqss_qir_qiskit-0.1.0.dist-info/WHEEL
mqss_qir_qiskit-0.1.0.dist-info/entry_points.txt
mqss_qir_qiskit-0.1.0.dist-info/licenses/LICENSE
mqss_qir_qiskit-0.1.0.dist-info/RECORD
