Metadata-Version: 2.1
Name: mqss-qir-qiskit
Version: 0.1.0
Summary: Tool to convert QIR to a Qiskit QuantumCircuit object
Keywords: MQSS,quantum-computing,Qiskit,qir
Author-Email: mqss <mqss@munich-quantum-valley.de>
License: Apache-2.0
Requires-Python: >=3.10
Requires-Dist: pyqir>=0.8.0
Requires-Dist: llvmlite>=0.40.1
Requires-Dist: qiskit<2.0.0,>=0.45
